pylexa/__init__.py
pylexa/app.py
pylexa/blueprint.py
pylexa/default_handlers.py
pylexa/exceptions.py
pylexa/intent.py
pylexa/request.py
pylexa/response.py
pylexa/verify.py
pylexa/tools/__init__.py
pylexa/tools/parse_conf.py
pylexa-1.0.0.dist-info/DESCRIPTION.rst
pylexa-1.0.0.dist-info/METADATA
pylexa-1.0.0.dist-info/RECORD
pylexa-1.0.0.dist-info/WHEEL
pylexa-1.0.0.dist-info/entry_points.txt
pylexa-1.0.0.dist-info/metadata.json
pylexa-1.0.0.dist-info/top_level.txt
tests/__init__.py
tests/integration/__init__.py
tests/integration/app_for_testing.py
tests/integration/test_intent.py
tests/integration/test_launch_request.py
tests/integration/test_session_ended_request.py
tests/integration/test_validation.py
tests/integration/tools/__init__.py
tests/integration/tools/test_parse_conf.py
tests/unit/__init__.py
tests/unit/test_app.py
tests/unit/test_default_handlers.py
tests/unit/test_intent.py
tests/unit/test_request.py
tests/unit/test_response.py
tests/unit/test_verify.py
