Metadata-Version: 2.0
Name: pylexa
Version: 1.0.0
Summary: A library to ease creation of an Alexa Skills Kit
Home-page: http://www.github.com/patricksmith/pylexa
Author: Patrick Smith
Author-email: pjs482@gmail.com
License: UNKNOWN
Keywords: amazon alexa ask
Platform: UNKNOWN
Classifier: Development Status :: 3 - Alpha
Classifier: Topic :: Utilities
Requires-Dist: flask
Requires-Dist: pycrypto
Requires-Dist: pyopenssl
Requires-Dist: python-dateutil
Requires-Dist: pyyaml
Requires-Dist: requests
